<?xml version="1.0"?>
<!DOCTYPE hibernate-mapping PUBLIC "-//Hibernate/Hibernate Mapping DTD 3.0//EN"
"http://www.hibernate.org/dtd/hibernate-mapping-3.0.dtd">
<!-- Generated Apr 30, 2017 1:09:31 AM by Hibernate Tools 4.3.1 -->
<hibernate-mapping>
    <class name="dvdrental.Wishlistitems" table="wishlistitems" catalog="sakila" optimistic-lock="version">
        <id name="wishItemsId" type="java.lang.Integer">
            <column name="wishItems_id" />
            <generator class="identity" />
        </id>
        <many-to-one name="wishlist" class="dvdrental.Wishlist" fetch="select">
            <column name="wishList_wishList_id" not-null="true" />
        </many-to-one>
        <property name="filmId" type="short">
            <column name="film_id" not-null="true" />
        </property>
    </class>
</hibernate-mapping>
